nonebot_plugin_zsmeme/__init__.py
nonebot_plugin_zsmeme/utils.py
nonebot_plugin_zsmeme-0.0.4.dist-info/LICENSE
nonebot_plugin_zsmeme-0.0.4.dist-info/METADATA
nonebot_plugin_zsmeme-0.0.4.dist-info/WHEEL
nonebot_plugin_zsmeme-0.0.4.dist-info/RECORD
