Metadata-Version: 2.1
Name: nonebot-plugin-zsmeme
Version: 0.0.4
Summary: 发送寰宇重工中的表情
Home-page: https://github.com/shi-yingyingjiang/nonebot-plugin-zsmeme
License: MIT
Author: shiyingyingjiang
Author-email: 2798134864@qq.com
Requires-Python: >=3.8
Classifier: License :: OSI Approved :: MIT License
Classifier: Programming Language :: Python :: 3
Classifier: Programming Language :: Python :: 3.8
Classifier: Programming Language :: Python :: 3.9
Classifier: Programming Language :: Python :: 3.10
Classifier: Programming Language :: Python :: 3.11
Classifier: Programming Language :: Python :: 3.12
Requires-Dist: httpx (>=0.27.0)
Requires-Dist: lxml (>=4.9.3)
Requires-Dist: nonebot-adapter-onebot (>=2.2.3)
Requires-Dist: nonebot2 (>=2.2.1)
Project-URL: Repository, https://github.com/shi-yingyingjiang/nonebot-plugin-zsmeme
